triggerd.py
triggerd-0.6.0.data/data/share/triggerd/examples/event.txt
triggerd-0.6.0.data/data/share/triggerd/examples/triggers.conf
triggerd-0.6.0.data/scripts/bash-config
triggerd-0.6.0.data/scripts/triggerd.sh
triggerd-0.6.0.dist-info/DESCRIPTION.rst
triggerd-0.6.0.dist-info/METADATA
triggerd-0.6.0.dist-info/RECORD
triggerd-0.6.0.dist-info/WHEEL
triggerd-0.6.0.dist-info/entry_points.txt
triggerd-0.6.0.dist-info/metadata.json
triggerd-0.6.0.dist-info/pbr.json
triggerd-0.6.0.dist-info/top_level.txt
